{"first_name":"Bastien","last_name":"Duclaux","permalink":"bastien-duclaux","crunchbase_url":"http://www.crunchbase.com/person/bastien-duclaux","homepage_url":"http://www.twenga.com","birthplace":"","twitter_username":null,"blog_url":"","blog_feed_url":"","affiliation_name":"Twenga","born_year":1975,"born_month":1,"born_day":25,"tag_list":"","alias_list":null,"created_at":"Sat Dec 08 05:34:48 UTC 2007","updated_at":"Fri Mar 13 21:40:24 UTC 2009","overview":null,"image":null,"degrees":[],"relationships":[{"is_past":false,"title":"Co-Founder, CEO","firm":{"name":"Twenga","permalink":"twenga","type_of_entity":"company","image":{"available_sizes":[[[150,44],"assets/images/resized/0000/2551/2551v5-max-150x150.png"],[[250,73],"assets/images/resized/0000/2551/2551v5-max-250x250.png"],[[450,132],"assets/images/resized/0000/2551/2551v5-max-450x450.png"]],"attribution":null}}}],"investments":[],"milestones":[],"video_embeds":[],"external_links":[],"web_presences":[]}