{"first_name":"Ben","last_name":"T. Smith, IV","permalink":"ben-t-smith-iv","crunchbase_url":"http://www.crunchbase.com/person/ben-t-smith-iv","homepage_url":null,"birthplace":null,"twitter_username":null,"blog_url":null,"blog_feed_url":null,"affiliation_name":"Mesmo.tv","born_year":null,"born_month":null,"born_day":null,"tag_list":"","alias_list":null,"created_at":"Fri Oct 05 11:32:28 UTC 2007","updated_at":"Thu May 24 02:07:29 UTC 2012","overview":"<p>Ben Smith is founder of online local advertising company MerchantCircle.  </p>","image":null,"degrees":[],"relationships":[{"is_past":false,"title":"CEO","firm":{"name":"Wanderful Media","permalink":"wanderful-media","type_of_entity":"company","image":{"available_sizes":[[[150,49],"assets/images/resized/0021/3069/213069v4-max-150x150.png"],[[250,82],"assets/images/resized/0021/3069/213069v4-max-250x250.png"],[[278,92],"assets/images/resized/0021/3069/213069v4-max-450x450.png"]],"attribution":null}}},{"is_past":false,"title":"Board","firm":{"name":"Mesmo.tv","permalink":"mesmo-tv","type_of_entity":"company","image":{"available_sizes":[[[150,28],"assets/images/resized/0000/1180/1180v1-max-150x150.png"],[[199,38],"assets/images/resized/0000/1180/1180v1-max-250x250.png"],[[199,38],"assets/images/resized/0000/1180/1180v1-max-450x450.png"]],"attribution":null}}}],"investments":[{"funding_round":{"round_code":"unattributed","source_url":"http://techcrunch.com/2012/08/27/wells-social-list-making-app-thinks-outside-the-to-do/","source_description":"Well’s Social List-Making App Thinks Outside The “To-Do”","raised_amount":1000000,"raised_currency_code":"USD","funded_year":2012,"funded_month":3,"funded_day":1,"company":{"name":"Well","permalink":"well-app","image":{"available_sizes":[[[116,118],"assets/images/resized/0020/8352/208352v1-max-150x150.png"],[[116,118],"assets/images/resized/0020/8352/208352v1-max-250x250.png"],[[116,118],"assets/images/resized/0020/8352/208352v1-max-450x450.png"]],"attribution":null}}}}],"milestones":[],"video_embeds":[],"external_links":[],"web_presences":[{"external_url":"http://btsiv.com","title":"Blog"},{"external_url":"http://twitter.com/#!/bentsmithfour","title":"Ben Smith Twitter"}]}