{"first_name":"Dan","last_name":"Rodgers","permalink":"dan-rodgers","crunchbase_url":"http://www.crunchbase.com/person/dan-rodgers","homepage_url":"http://danrodgers.co.uk","birthplace":"Swindon, UK","twitter_username":"dansgalaxy","blog_url":"http://dansgalaxy.co.uk","blog_feed_url":"http://dansgalaxy.co.uk/feed/","affiliation_name":"XDnet Web Services","born_year":1992,"born_month":3,"born_day":25,"tag_list":"web-developer, web-hosting","alias_list":null,"created_at":"Wed Jun 29 21:15:31 UTC 2011","updated_at":"Fri Jul 01 04:48:50 UTC 2011","overview":"<p>Dan is a Technology lover, Web-developer, working on many web projects as well as managing his Web Hosting &amp; Web Services business XDnet.co.uk. </p>","image":{"available_sizes":[[[150,127],"assets/images/resized/0014/1823/141823v2-max-150x150.jpg"],[[250,212],"assets/images/resized/0014/1823/141823v2-max-250x250.jpg"],[[450,382],"assets/images/resized/0014/1823/141823v2-max-450x450.jpg"]],"attribution":""},"degrees":[],"relationships":[{"is_past":false,"title":"Director","firm":{"name":"XDnet","permalink":"xdnet","type_of_entity":"company","image":{"available_sizes":[[[150,50],"assets/images/resized/0002/7621/27621v2-max-150x150.jpg"],[[250,84],"assets/images/resized/0002/7621/27621v2-max-250x250.jpg"],[[341,115],"assets/images/resized/0002/7621/27621v2-max-450x450.jpg"]],"attribution":null}}}],"investments":[],"milestones":[],"video_embeds":[],"external_links":[],"web_presences":[{"external_url":"http://twitter.com/dansgalaxy","title":"@dansgalaxy"},{"external_url":"http://uk.linkedin.com/in/danjrordgers","title":"LinkedIn"}]}