{"first_name":"Harold","last_name":"Levy","permalink":"harold-levy","crunchbase_url":"http://www.crunchbase.com/person/harold-levy","homepage_url":null,"birthplace":null,"twitter_username":null,"blog_url":null,"blog_feed_url":null,"affiliation_name":"Unaffiliated","born_year":null,"born_month":null,"born_day":null,"tag_list":null,"alias_list":null,"created_at":"Tue Dec 06 02:43:26 UTC 2011","updated_at":"Tue Dec 06 02:43:26 UTC 2011","overview":null,"image":null,"degrees":[],"relationships":[],"investments":[{"funding_round":{"round_code":"seed","source_url":"http://techcrunch.com/2011/12/05/late-nite-labs-raises-1-1-million-to-bring-virtual-science-education-to-campuses/","source_description":"Late Nite Labs Raises $1.1 Million To Bring Virtual Science Education To Campuses","raised_amount":1100000,"raised_currency_code":"USD","funded_year":2011,"funded_month":12,"funded_day":5,"company":{"name":"Late Nite Labs","permalink":"late-nite-labs","image":{"available_sizes":[[[150,68],"assets/images/resized/0015/6645/156645v2-max-150x150.png"],[[250,113],"assets/images/resized/0015/6645/156645v2-max-250x250.png"],[[317,144],"assets/images/resized/0015/6645/156645v2-max-450x450.png"]],"attribution":null}}}}],"milestones":[],"video_embeds":[],"external_links":[],"web_presences":[]}