{"first_name":"Jason","last_name":"Port","permalink":"jason-port-2","crunchbase_url":"http://www.crunchbase.com/person/jason-port-2","homepage_url":"http://www.quirky.com","birthplace":"Brooklyn, NY","twitter_username":"portodog","blog_url":"","blog_feed_url":"","affiliation_name":"Quirky.com","born_year":1970,"born_month":8,"born_day":7,"tag_list":"","alias_list":null,"created_at":"Wed Jun 09 21:43:29 UTC 2010","updated_at":"Thu Feb 17 02:55:59 UTC 2011","overview":"<p>Strategic Thinker, Seed Investor who has a &#8220;knack&#8221; for discovering successful entrepenuers, and early staged companies.</p>\n\n<p>Identifying, developing and executing exemplary sales/marketing models to support strategic business goals and objectives, and building relationships with potential partner companies and customers to facilitate outstanding revenue opportunities</p>","image":null,"degrees":[{"degree_type":"BA","subject":"Business, HotDog Vending","institution":"University Of Maryland","graduated_year":1992,"graduated_month":null,"graduated_day":null}],"relationships":[{"is_past":true,"title":"M&A Development ","firm":{"name":"The Wicks Group","permalink":"the-wicks-group","type_of_entity":"company","image":null}},{"is_past":true,"title":"Director Strategic Sales","firm":{"name":"Sportsline","permalink":"sportsline","type_of_entity":"company","image":{"available_sizes":[[[150,56],"assets/images/resized/0009/7748/97748v1-max-150x150.jpg"],[[183,69],"assets/images/resized/0009/7748/97748v1-max-250x250.jpg"],[[183,69],"assets/images/resized/0009/7748/97748v1-max-450x450.jpg"]],"attribution":null}}},{"is_past":true,"title":"Brave Soul","firm":{"name":"quirky","permalink":"quirky","type_of_entity":"company","image":{"available_sizes":[[[150,150],"assets/images/resized/0004/6233/46233v8-max-150x150.jpg"],[[250,250],"assets/images/resized/0004/6233/46233v8-max-250x250.jpg"],[[450,450],"assets/images/resized/0004/6233/46233v8-max-450x450.jpg"]],"attribution":null}}}],"investments":[{"funding_round":{"round_code":"seed","source_url":"http://blog.makezine.com/archive/2011/10/open-source-hardware-company-littlebits-closes-first-round-of-financing-enters-moma-collection.html","source_description":"Open-source Hardware Company littleBits Closes First Round of Financing, Enters MoMA Collection!","raised_amount":null,"raised_currency_code":"USD","funded_year":2011,"funded_month":9,"funded_day":1,"company":{"name":"littleBits","permalink":"littlebits","image":{"available_sizes":[[[150,71],"assets/images/resized/0016/6025/166025v2-max-150x150.jpg"],[[250,118],"assets/images/resized/0016/6025/166025v2-max-250x250.jpg"],[[450,213],"assets/images/resized/0016/6025/166025v2-max-450x450.jpg"]],"attribution":null}}}}],"milestones":[{"description":"Founding Investor @ Quirky.com","stoned_year":2009,"stoned_month":2,"stoned_day":1,"source_url":"","source_text":null,"source_description":"Founding Investor Quirky.com","stoneable_type":"Person","stoned_value":null,"stoned_value_type":null,"stoned_acquirer":null,"stoneable":{"first_name":"Jason","last_name":"Port","permalink":"jason-port-2"}},{"description":"Investor Ringleader Digital Media","stoned_year":2010,"stoned_month":10,"stoned_day":1,"source_url":"","source_text":null,"source_description":"","stoneable_type":"Person","stoned_value":null,"stoned_value_type":null,"stoned_acquirer":null,"stoneable":{"first_name":"Jason","last_name":"Port","permalink":"jason-port-2"}},{"description":"Angel Investor Uber","stoned_year":2010,"stoned_month":null,"stoned_day":null,"source_url":"","source_text":null,"source_description":"","stoneable_type":"Person","stoned_value":null,"stoned_value_type":null,"stoned_acquirer":null,"stoneable":{"first_name":"Jason","last_name":"Port","permalink":"jason-port-2"}},{"description":"Investor JumpForward","stoned_year":2010,"stoned_month":null,"stoned_day":null,"source_url":"","source_text":null,"source_description":"","stoneable_type":"Person","stoned_value":null,"stoned_value_type":null,"stoned_acquirer":null,"stoneable":{"first_name":"Jason","last_name":"Port","permalink":"jason-port-2"}}],"video_embeds":[],"external_links":[],"web_presences":[]}