{"first_name":"Jeff","last_name":"Rechtman","permalink":"jeff-rechtman","crunchbase_url":"http://www.crunchbase.com/person/jeff-rechtman","homepage_url":"","birthplace":"Miami Beach","twitter_username":"jeffrechtman","blog_url":"","blog_feed_url":"","affiliation_name":"Unaffiliated","born_year":1986,"born_month":6,"born_day":25,"tag_list":"","alias_list":null,"created_at":"Wed Oct 17 20:52:49 UTC 2012","updated_at":"Wed Oct 31 00:24:21 UTC 2012","overview":"<p>In-House counsel at Grooveshark.com</p>","image":null,"degrees":[{"degree_type":"Juris Doctor","subject":"Corporate Law; Entrepreneurship","institution":"University of Florida Levin College of Law","graduated_year":2012,"graduated_month":null,"graduated_day":null}],"relationships":[],"investments":[],"milestones":[],"video_embeds":[],"external_links":[],"web_presences":[]}