{"first_name":"John","last_name":"Taylor","permalink":"john-taylor-4","crunchbase_url":"http://www.crunchbase.com/person/john-taylor-4","homepage_url":"http://www.designawebsite.com.au/","birthplace":"","twitter_username":"","blog_url":"http://web-developer-melbourne.com.au/","blog_feed_url":"http://www.web-developer-melbourne.com.au/feed/","affiliation_name":"Unaffiliated","born_year":null,"born_month":null,"born_day":null,"tag_list":"","alias_list":null,"created_at":"Thu Apr 19 09:25:57 UTC 2012","updated_at":"Tue Apr 24 22:15:32 UTC 2012","overview":"","image":null,"degrees":[],"relationships":[],"investments":[],"milestones":[],"video_embeds":[],"external_links":[],"web_presences":[]}