{"first_name":"Lawrence","last_name":"Hall","permalink":"lawrence-hall","crunchbase_url":"http://www.crunchbase.com/person/lawrence-hall","homepage_url":"http://www.zoopla.co.uk/","birthplace":"","twitter_username":"lawrencejhall","blog_url":"","blog_feed_url":"","affiliation_name":"Unaffiliated","born_year":null,"born_month":null,"born_day":null,"tag_list":"","alias_list":null,"created_at":"Thu May 10 21:11:29 UTC 2012","updated_at":"Fri May 11 04:35:03 UTC 2012","overview":"<p>Head of PR at innovative property website, Zoopla.co.uk.</p>\n\n<p>Twelve years first class corporate, consumer and digital experience working in both agency and in-house environments.</p>","image":{"available_sizes":[[[99,150],"assets/images/resized/0018/8996/188996v2-max-150x150.jpg"],[[166,250],"assets/images/resized/0018/8996/188996v2-max-250x250.jpg"],[[298,450],"assets/images/resized/0018/8996/188996v2-max-450x450.jpg"]],"attribution":"<p>Lawrence Hall</p>"},"degrees":[],"relationships":[],"investments":[],"milestones":[],"video_embeds":[],"external_links":[],"web_presences":[{"external_url":"https://twitter.com/LawrenceJHall","title":"Twitter"}]}