{"first_name":"Leland","last_name":"Robinson","permalink":"leland-robinson","crunchbase_url":"http://www.crunchbase.com/person/leland-robinson","homepage_url":"http://Muzieo.com","birthplace":"New York NY","twitter_username":"Muzieo","blog_url":"","blog_feed_url":"","affiliation_name":"MuzieoMedia inc.","born_year":1988,"born_month":6,"born_day":2,"tag_list":"","alias_list":null,"created_at":"Sun Mar 25 01:22:59 UTC 2012","updated_at":"Sun Apr 01 13:25:15 UTC 2012","overview":"<p>Leland Robinson is American Entrepreneur and Music composer and startup founder of a disruptive mobile based application service called Muzieo.</p>","image":null,"degrees":[],"relationships":[{"is_past":false,"title":"Founder and CEO","firm":{"name":"Muzieo Media","permalink":"muzieo-media","type_of_entity":"company","image":{"available_sizes":[[[150,56],"assets/images/resized/0021/7557/217557v2-max-150x150.png"],[[250,93],"assets/images/resized/0021/7557/217557v2-max-250x250.png"],[[383,143],"assets/images/resized/0021/7557/217557v2-max-450x450.png"]],"attribution":null}}}],"investments":[],"milestones":[],"video_embeds":[],"external_links":[],"web_presences":[{"external_url":"http://Muzieo.com","title":""}]}