{"first_name":"Len","last_name":"L. Mizrah","permalink":"len-l-mizrah","crunchbase_url":"http://www.crunchbase.com/person/len-l-mizrah","homepage_url":null,"birthplace":null,"twitter_username":null,"blog_url":null,"blog_feed_url":null,"affiliation_name":"Unaffiliated","born_year":null,"born_month":null,"born_day":null,"tag_list":null,"alias_list":null,"created_at":"Mon Apr 26 01:08:47 UTC 2010","updated_at":"Mon Apr 26 01:08:47 UTC 2010","overview":null,"image":null,"degrees":[],"relationships":[{"is_past":false,"title":"President & CEO","firm":{"name":"Authernative","permalink":"authernative","type_of_entity":"company","image":{"available_sizes":[[[150,24],"assets/images/resized/0008/4877/84877v1-max-150x150.png"],[[250,40],"assets/images/resized/0008/4877/84877v1-max-250x250.png"],[[255,41],"assets/images/resized/0008/4877/84877v1-max-450x450.png"]],"attribution":null}}}],"investments":[],"milestones":[],"video_embeds":[],"external_links":[],"web_presences":[]}