{"first_name":"Luca","last_name":"Candela","permalink":"luca-candela","crunchbase_url":"http://www.crunchbase.com/person/luca-candela","homepage_url":null,"birthplace":null,"twitter_username":null,"blog_url":null,"blog_feed_url":null,"affiliation_name":"WujWuj","born_year":null,"born_month":null,"born_day":null,"tag_list":"ux, pm, usability","alias_list":null,"created_at":"Sun May 18 06:33:55 UTC 2008","updated_at":"Mon Sep 26 02:11:23 UTC 2011","overview":"<p>Luca was born in 1978 in Italy. He worked as graphic designer, programmer, then project manager and IT manager, lives and breathes the Internet, knows how to make the web &#8220;just work&#8221; and communicates his vision through his natural skills for prototyping.</p>\n\n<p>He is currently living in the Bay Area and working as Product Manager for HumanConcepts, global leader in on-demand workforce decision support solutions and the maker of OrgPlus.</p>\n\n<p>Luca has a degree in computer science and studied e-learning, artificial intelligence and human-computer interaction at the University of Turin in Italy and at the Universidad Autonoma de Madrid in Spain.</p>\n\n<p>This is what people said about him:</p>\n\n<p>&#8230;he is a massively talented guy.  He is a master of prototyping and usability&#8230; He’s one of the few people that normally leaves after me.  And he’ll come in on weekends and do whatever it takes to meet the deadline&#8230;</p>\n\n<p>Jason Berry (CEO of topLingo Development Inc.)</p>","image":{"available_sizes":[[[150,99],"assets/images/resized/0004/2171/42171v2-max-150x150.jpg"],[[250,166],"assets/images/resized/0004/2171/42171v2-max-250x250.jpg"],[[450,299],"assets/images/resized/0004/2171/42171v2-max-450x450.jpg"]],"attribution":"<p>Scott Beale / <a href=\"http://www.luckymethod.com\" title=\"Luckymethod.com\" rel=\"nofollow\">Luckymethod.com</a></p>"},"degrees":[{"degree_type":"MS","subject":"Computer Science","institution":"Universita' degli Studi di Torino","graduated_year":2005,"graduated_month":null,"graduated_day":null}],"relationships":[{"is_past":false,"title":"","firm":{"name":"Mistake","permalink":"mistake","type_of_entity":"company","image":null}},{"is_past":true,"title":"Project Manager","firm":{"name":"WujWuj","permalink":"wujwuj","type_of_entity":"company","image":{"available_sizes":[[[150,33],"assets/images/resized/0001/8782/18782v1-max-150x150.jpg"],[[250,55],"assets/images/resized/0001/8782/18782v1-max-250x250.jpg"],[[345,76],"assets/images/resized/0001/8782/18782v1-max-450x450.jpg"]],"attribution":null}}},{"is_past":true,"title":"Producer","firm":{"name":"igniteHealth","permalink":"ignitehealth","type_of_entity":"company","image":null}},{"is_past":true,"title":"Project Manager","firm":{"name":"LioNBRIDGE Technology","permalink":"lionbridge-technology","type_of_entity":"company","image":{"available_sizes":[[[150,45],"assets/images/resized/0008/6057/86057v1-max-150x150.png"],[[222,68],"assets/images/resized/0008/6057/86057v1-max-250x250.png"],[[222,68],"assets/images/resized/0008/6057/86057v1-max-450x450.png"]],"attribution":null}}},{"is_past":true,"title":"UX Designer","firm":{"name":"YourVersion","permalink":"yourversion","type_of_entity":"company","image":{"available_sizes":[[[150,29],"assets/images/resized/0005/6218/56218v2-max-150x150.png"],[[215,42],"assets/images/resized/0005/6218/56218v2-max-250x250.png"],[[215,42],"assets/images/resized/0005/6218/56218v2-max-450x450.png"]],"attribution":null}}},{"is_past":true,"title":"","firm":{"name":"Sencha","permalink":"sencha","type_of_entity":"company","image":{"available_sizes":[[[120,50],"assets/images/resized/0009/1563/91563v1-max-150x150.png"],[[120,50],"assets/images/resized/0009/1563/91563v1-max-250x250.png"],[[120,50],"assets/images/resized/0009/1563/91563v1-max-450x450.png"]],"attribution":null}}},{"is_past":true,"title":"","firm":{"name":"Mistake","permalink":"mistake","type_of_entity":"company","image":null}},{"is_past":true,"title":"Project  Mangler","firm":{"name":"topLingo Development","permalink":"toplingo","type_of_entity":"company","image":{"available_sizes":[[[135,35],"assets/images/resized/0002/1773/21773v1-max-150x150.png"],[[135,35],"assets/images/resized/0002/1773/21773v1-max-250x250.png"],[[135,35],"assets/images/resized/0002/1773/21773v1-max-450x450.png"]],"attribution":null}}},{"is_past":true,"title":"Multimedia Specialist","firm":{"name":"LioNBRIDGE Technology","permalink":"lionbridge-technology","type_of_entity":"company","image":{"available_sizes":[[[150,45],"assets/images/resized/0008/6057/86057v1-max-150x150.png"],[[222,68],"assets/images/resized/0008/6057/86057v1-max-250x250.png"],[[222,68],"assets/images/resized/0008/6057/86057v1-max-450x450.png"]],"attribution":null}}},{"is_past":true,"title":"Product Manager","firm":{"name":"HumanConcepts","permalink":"humanconcepts","type_of_entity":"company","image":{"available_sizes":[[[150,27],"assets/images/resized/0006/7507/67507v2-max-150x150.png"],[[209,39],"assets/images/resized/0006/7507/67507v2-max-250x250.png"],[[209,39],"assets/images/resized/0006/7507/67507v2-max-450x450.png"]],"attribution":null}}},{"is_past":true,"title":"Product Manager","firm":{"name":"Trubates","permalink":"trubates","type_of_entity":"company","image":{"available_sizes":[[[150,32],"assets/images/resized/0013/0940/130940v2-max-150x150.jpg"],[[168,36],"assets/images/resized/0013/0940/130940v2-max-250x250.jpg"],[[168,36],"assets/images/resized/0013/0940/130940v2-max-450x450.jpg"]],"attribution":null}}},{"is_past":true,"title":"","firm":{"name":"Sencha","permalink":"sencha","type_of_entity":"company","image":{"available_sizes":[[[120,50],"assets/images/resized/0009/1563/91563v1-max-150x150.png"],[[120,50],"assets/images/resized/0009/1563/91563v1-max-250x250.png"],[[120,50],"assets/images/resized/0009/1563/91563v1-max-450x450.png"]],"attribution":null}}}],"investments":[],"milestones":[{"description":"Founded the SFBAYUX group to promote the cross-pollination between user experience professionals and developers in the San Francisco Bay Area.","stoned_year":2009,"stoned_month":9,"stoned_day":25,"source_url":"http://www.meetup.com/sfbayux/about/","source_text":null,"source_description":"","stoneable_type":"Person","stoned_value":null,"stoned_value_type":null,"stoned_acquirer":null,"stoneable":{"first_name":"Luca","last_name":"Candela","permalink":"luca-candela"}}],"video_embeds":[],"external_links":[],"web_presences":[]}