{"first_name":"Marcin","last_name":"Zduniak","permalink":"marcin-zduniak","crunchbase_url":"http://www.crunchbase.com/person/marcin-zduniak","homepage_url":"http://www.zduniak.com","birthplace":"","twitter_username":null,"blog_url":"http://www.mobiledeveloper.pl/articles/zduniakm","blog_feed_url":"http://www.mobiledeveloper.pl/blog/1004/feed","affiliation_name":"Colubris Consulting","born_year":1983,"born_month":null,"born_day":null,"tag_list":"j2me, mobile, it, technology, poland, consultant, contractor, freelancer","alias_list":null,"created_at":"Fri Jun 06 07:46:55 UTC 2008","updated_at":"Sun Dec 07 12:52:18 UTC 2008","overview":null,"image":{"available_sizes":[[[63,85],"assets/images/resized/0003/1166/31166v2-max-150x150.jpg"],[[63,85],"assets/images/resized/0003/1166/31166v2-max-250x250.jpg"],[[63,85],"assets/images/resized/0003/1166/31166v2-max-450x450.jpg"]],"attribution":""},"degrees":[],"relationships":[{"is_past":false,"title":"CEO","firm":{"name":"Colubris Consulting","permalink":"mobile-technology-lab","type_of_entity":"company","image":{"available_sizes":[[[143,59],"assets/images/resized/0002/0036/20036v5-max-150x150.png"],[[143,59],"assets/images/resized/0002/0036/20036v5-max-250x250.png"],[[143,59],"assets/images/resized/0002/0036/20036v5-max-450x450.png"]],"attribution":null}}}],"investments":[],"milestones":[],"video_embeds":[],"external_links":[],"web_presences":[]}