{"first_name":"Mihran","last_name":"Papazian","permalink":"mihran-papazian-2","crunchbase_url":"http://www.crunchbase.com/person/mihran-papazian-2","homepage_url":"http://mihranig.com","birthplace":"Paris","twitter_username":"mihranig","blog_url":"http://blog.mihranig.com","blog_feed_url":"http://blog.mihranig.com/feed","affiliation_name":"StreamTease International Ltd.","born_year":1982,"born_month":12,"born_day":8,"tag_list":"mihran, papazian, dianboom, streamtease, ppz, web, api, php, as3, away3d","alias_list":null,"created_at":"Tue Jul 20 06:16:56 UTC 2010","updated_at":"Mon Aug 15 17:46:31 UTC 2011","overview":"<p>Mihran Papazian is born and raise in Paris and has studied in the USA.\nHe moved to Shenzhen, China end 2006 and launched an Imp-Exp company that now provides end-to-end service solutions.\nAfter getting familiar with the language and the ways Chinese handle business he launched a web startup early 2010: dianboom. Mihran is willing to be an active segment on the convergence of western technologies and China capacity.</p>","image":{"available_sizes":[[[150,112],"assets/images/resized/0009/4242/94242v2-max-150x150.jpg"],[[250,187],"assets/images/resized/0009/4242/94242v2-max-250x250.jpg"],[[450,337],"assets/images/resized/0009/4242/94242v2-max-450x450.jpg"]],"attribution":""},"degrees":[{"degree_type":"MBA","subject":"Finance & Management","institution":"St John's University NYC","graduated_year":2006,"graduated_month":null,"graduated_day":null},{"degree_type":"College","subject":"International Management","institution":"ISEG Paris","graduated_year":2005,"graduated_month":null,"graduated_day":null}],"relationships":[{"is_past":true,"title":"Founder & CEO","firm":{"name":"dianboom","permalink":"dianboom","type_of_entity":"company","image":{"available_sizes":[[[150,42],"assets/images/resized/0009/4241/94241v4-max-150x150.png"],[[250,70],"assets/images/resized/0009/4241/94241v4-max-250x250.png"],[[450,126],"assets/images/resized/0009/4241/94241v4-max-450x450.png"]],"attribution":null}}},{"is_past":true,"title":"Founder","firm":{"name":"StreamTease International Ltd.","permalink":"streamtease-international-ltd","type_of_entity":"company","image":{"available_sizes":[[[150,97],"assets/images/resized/0009/4392/94392v2-max-150x150.png"],[[250,163],"assets/images/resized/0009/4392/94392v2-max-250x250.png"],[[450,293],"assets/images/resized/0009/4392/94392v2-max-450x450.png"]],"attribution":null}}},{"is_past":true,"title":"Board Director","firm":{"name":"PPZ Assets Holding Corp.","permalink":"ppz-assets-holding-corp","type_of_entity":"financial_org","image":null}}],"investments":[],"milestones":[],"video_embeds":[],"external_links":[],"web_presences":[{"external_url":"http://twitter.com/mihranig","title":"Twitter"},{"external_url":"http://facebook.com/mihran.papazian","title":"Facebook"},{"external_url":"http://www.linkedin.com/profile?viewProfile=&key=39595985&trk=tab_pro","title":"LinkedIn"},{"external_url":"http://mihranig.com","title":"Website"},{"external_url":"http://blog.mihranig.com","title":"Blog"},{"external_url":"http://www.weibo.com/mihranig","title":"æ–°æµªå¾®æ³¢"},{"external_url":"http://t.qq.com/mihranig","title":"è…¾è®¯å¾®åš"}]}