{"first_name":"Monjurul","last_name":"Dolon","permalink":"monjurul-dolon","crunchbase_url":"http://www.crunchbase.com/person/monjurul-dolon","homepage_url":"","birthplace":"","twitter_username":null,"blog_url":null,"blog_feed_url":null,"affiliation_name":"iJigg","born_year":null,"born_month":null,"born_day":null,"tag_list":null,"alias_list":null,"created_at":"Mon Aug 27 19:36:27 UTC 2007","updated_at":"Mon Feb 18 06:08:38 UTC 2008","overview":null,"image":null,"degrees":[],"relationships":[{"is_past":false,"title":"Founder","firm":{"name":"PIKAGame","permalink":"pikagame","type_of_entity":"company","image":{"available_sizes":[[[150,53],"assets/images/resized/0003/2627/32627v4-max-150x150.png"],[[249,88],"assets/images/resized/0003/2627/32627v4-max-250x250.png"],[[249,88],"assets/images/resized/0003/2627/32627v4-max-450x450.png"]],"attribution":null}}}],"investments":[],"milestones":[],"video_embeds":[],"external_links":[],"web_presences":[]}