{"first_name":"Preston","last_name":"Padden","permalink":"preston-padden","crunchbase_url":"http://www.crunchbase.com/person/preston-padden","homepage_url":null,"birthplace":null,"twitter_username":null,"blog_url":null,"blog_feed_url":null,"affiliation_name":"Unaffiliated","born_year":null,"born_month":null,"born_day":null,"tag_list":null,"alias_list":null,"created_at":"Wed May 21 02:33:58 UTC 2008","updated_at":"Wed May 21 02:50:08 UTC 2008","overview":"<p>Preston Padden became executive vice president of government relations for The Walt Disney Company in July, 1998. Based in Washington, D.C., he works with all business units of The Walt Disney Company in their interactions with the U.S. government and those of other countries.</p>\n\n<p>Previously he was president, ABC Television Network.</p>\n\n<p>Before joining ABC in 1997, Padden was chairman and chief executive officer of American Sky Broadcasting (ASkyB), a satellite television joint venture between News Corporation and MCI. Prior to joining ASkyB, he had served as president, telecommunications and television, for News Corporation, having joined Fox Broadcasting Company in January, 1990, as senior vice president, Affiliates.</p>\n\n<p>Born on November 26, 1948 in Washington, D.C., he received his undergraduate degree from the University of Maryland and his law degree from George Washington University in Washington, D.C. Padden and his wife Barbara are the parents of three children and live in Potomac, MD. </p>","image":{"available_sizes":[[[150,150],"assets/images/resized/0001/8990/18990v1-max-150x150.jpg"],[[200,200],"assets/images/resized/0001/8990/18990v1-max-250x250.jpg"],[[200,200],"assets/images/resized/0001/8990/18990v1-max-450x450.jpg"]],"attribution":"<p><a href=\"http://corporate.disney.go.com/corporate/management_team.html\" title=\"Disney\" rel=\"nofollow\">Disney</a></p>"},"degrees":[],"relationships":[{"is_past":false,"title":"Executive Vice President Government Relations, The Walt Disney Company","firm":{"name":"The Walt Disney Company","permalink":"the-walt-disney-company","type_of_entity":"company","image":{"available_sizes":[[[150,73],"assets/images/resized/0001/0929/10929v1-max-150x150.png"],[[165,81],"assets/images/resized/0001/0929/10929v1-max-250x250.png"],[[165,81],"assets/images/resized/0001/0929/10929v1-max-450x450.png"]],"attribution":null}}}],"investments":[],"milestones":[],"video_embeds":[],"external_links":[],"web_presences":[]}