{"first_name":"Ron","last_name":"Kurti","permalink":"ron-kurti","crunchbase_url":"http://www.crunchbase.com/person/ron-kurti","homepage_url":null,"birthplace":null,"twitter_username":null,"blog_url":null,"blog_feed_url":null,"affiliation_name":"Dopetracks","born_year":null,"born_month":null,"born_day":null,"tag_list":"","alias_list":null,"created_at":"Tue Feb 05 22:41:41 UTC 2008","updated_at":"Mon Nov 08 18:58:36 UTC 2010","overview":"<p>Ron Kurti is a User Experience Director, Photographer, and Music Producer based in San Francisco.</p>","image":{"available_sizes":[[[81,150],"assets/images/resized/0010/9062/109062v2-max-150x150.jpg"],[[136,250],"assets/images/resized/0010/9062/109062v2-max-250x250.jpg"],[[245,450],"assets/images/resized/0010/9062/109062v2-max-450x450.jpg"]],"attribution":""},"degrees":[{"degree_type":"BFA","subject":"Product Design","institution":"Carnegie Mellon University","graduated_year":1997,"graduated_month":null,"graduated_day":null}],"relationships":[{"is_past":false,"title":"Co-founder","firm":{"name":"Dopetracks","permalink":"dopetracks","type_of_entity":"company","image":{"available_sizes":[[[150,75],"assets/images/resized/0000/0778/778v1-max-150x150.png"],[[180,90],"assets/images/resized/0000/0778/778v1-max-250x250.png"],[[180,90],"assets/images/resized/0000/0778/778v1-max-450x450.png"]],"attribution":null}}},{"is_past":false,"title":"User Experience Director","firm":{"name":"Vast","permalink":"vast","type_of_entity":"company","image":{"available_sizes":[[[130,63],"assets/images/resized/0002/5280/25280v1-max-150x150.png"],[[130,63],"assets/images/resized/0002/5280/25280v1-max-250x250.png"],[[130,63],"assets/images/resized/0002/5280/25280v1-max-450x450.png"]],"attribution":null}}},{"is_past":true,"title":"Founder","firm":{"name":"Futuretrax","permalink":"futuretrax","type_of_entity":"company","image":null}},{"is_past":true,"title":"Creative Director","firm":{"name":"Echo Networks, Inc.","permalink":"echo-networks-inc","type_of_entity":"company","image":null}},{"is_past":true,"title":"Associate Designer","firm":{"name":"Hauser Design","permalink":"hauser-design","type_of_entity":"company","image":null}},{"is_past":true,"title":"Technical Director","firm":{"name":"COATO","permalink":"coato","type_of_entity":"company","image":{"available_sizes":[[[100,80],"assets/images/resized/0011/1387/111387v1-max-150x150.png"],[[100,80],"assets/images/resized/0011/1387/111387v1-max-250x250.png"],[[100,80],"assets/images/resized/0011/1387/111387v1-max-450x450.png"]],"attribution":null}}}],"investments":[],"milestones":[],"video_embeds":[],"external_links":[],"web_presences":[{"external_url":"http://ron.kurti.com","title":"Personal Site"}]}