{"first_name":"Ryan","last_name":"Gardner","permalink":"ryan-gardener","crunchbase_url":"http://www.crunchbase.com/person/ryan-gardener","homepage_url":"","birthplace":"","twitter_username":"","blog_url":"","blog_feed_url":"","affiliation_name":"Noterly","born_year":null,"born_month":null,"born_day":null,"tag_list":"","alias_list":null,"created_at":"Tue Mar 02 21:45:14 UTC 2010","updated_at":"Tue Mar 16 00:18:16 UTC 2010","overview":"<p>Ryan Gardner is a New York City based, business strategy director and web entrepreneur.</p>","image":{"available_sizes":[[[150,114],"assets/images/resized/0008/0451/80451v2-max-150x150.jpg"],[[221,169],"assets/images/resized/0008/0451/80451v2-max-250x250.jpg"],[[221,169],"assets/images/resized/0008/0451/80451v2-max-450x450.jpg"]],"attribution":""},"degrees":[],"relationships":[{"is_past":false,"title":"Co-Founder","firm":{"name":"Noterly","permalink":"noterly","type_of_entity":"company","image":{"available_sizes":[[[113,51],"assets/images/resized/0007/8840/78840v17-max-150x150.png"],[[113,51],"assets/images/resized/0007/8840/78840v17-max-250x250.png"],[[113,51],"assets/images/resized/0007/8840/78840v17-max-450x450.png"]],"attribution":null}}},{"is_past":false,"title":"President","firm":{"name":"Small Wonders","permalink":"small-wonders","type_of_entity":"company","image":{"available_sizes":[[[74,69],"assets/images/resized/0008/1945/81945v5-max-150x150.png"],[[74,69],"assets/images/resized/0008/1945/81945v5-max-250x250.png"],[[74,69],"assets/images/resized/0008/1945/81945v5-max-450x450.png"]],"attribution":null}}},{"is_past":true,"title":"Director of Strategic Development","firm":{"name":"Passenger","permalink":"think-passenger","type_of_entity":"company","image":{"available_sizes":[[[150,28],"assets/images/resized/0001/8395/18395v1-max-150x150.png"],[[164,31],"assets/images/resized/0001/8395/18395v1-max-250x250.png"],[[164,31],"assets/images/resized/0001/8395/18395v1-max-450x450.png"]],"attribution":null}}}],"investments":[],"milestones":[],"video_embeds":[],"external_links":[],"web_presences":[{"external_url":"http://www.ryangardn3r.com","title":""},{"external_url":"http://www.linkedin.com/in/ryangardn3r","title":"LinkedIn"},{"external_url":"http://twitter.com/ryangardn3r","title":"Twitter"}]}