{"first_name":"Tom","last_name":"Carter","permalink":"tom-carter-2","crunchbase_url":"http://www.crunchbase.com/person/tom-carter-2","homepage_url":"http://www.fountainpartners.com","birthplace":"","twitter_username":"tom__carter","blog_url":"","blog_feed_url":"","affiliation_name":"Fountain Partners","born_year":null,"born_month":null,"born_day":null,"tag_list":"","alias_list":null,"created_at":"Wed Mar 04 19:53:18 UTC 2009","updated_at":"Sat Dec 17 00:58:01 UTC 2011","overview":null,"image":{"available_sizes":[[[119,150],"assets/images/resized/0013/6462/136462v2-max-150x150.jpg"],[[184,231],"assets/images/resized/0013/6462/136462v2-max-250x250.jpg"],[[184,231],"assets/images/resized/0013/6462/136462v2-max-450x450.jpg"]],"attribution":"<p>jmarms</p>"},"degrees":[],"relationships":[{"is_past":false,"title":"Founder","firm":{"name":"Fountain Partners","permalink":"fountain-partners","type_of_entity":"financial_org","image":{"available_sizes":[[[150,100],"assets/images/resized/0003/9268/39268v4-max-150x150.jpg"],[[250,166],"assets/images/resized/0003/9268/39268v4-max-250x250.jpg"],[[432,288],"assets/images/resized/0003/9268/39268v4-max-450x450.jpg"]],"attribution":null}}},{"is_past":false,"title":"Co-Founder","firm":{"name":"Matchpin","permalink":"matchpin","type_of_entity":"company","image":{"available_sizes":[[[150,75],"assets/images/resized/0014/9905/149905v2-max-150x150.jpg"],[[200,100],"assets/images/resized/0014/9905/149905v2-max-250x250.jpg"],[[200,100],"assets/images/resized/0014/9905/149905v2-max-450x450.jpg"]],"attribution":null}}},{"is_past":true,"title":"CFO","firm":{"name":"Starmine","permalink":"starmine","type_of_entity":"company","image":{"available_sizes":[[[150,32],"assets/images/resized/0006/7256/67256v1-max-150x150.png"],[[188,41],"assets/images/resized/0006/7256/67256v1-max-250x250.png"],[[188,41],"assets/images/resized/0006/7256/67256v1-max-450x450.png"]],"attribution":null}}}],"investments":[],"milestones":[],"video_embeds":[],"external_links":[],"web_presences":[{"external_url":"http://www.linkedin.com/in/tomcarter","title":"LinkedIn"},{"external_url":"http://fountainpartners.com/about-us-fountain-partners/fountain-partners-team/about-tom-carter/","title":"Fountain Partners"},{"external_url":"http://angel.co/tomcarter","title":"AngelList"}]}