{"first_name":"Trudy M.","last_name":"Smit, CFA","permalink":"trudy-smit","crunchbase_url":"http://www.crunchbase.com/person/trudy-smit","homepage_url":"http://www.loaninterchange.com","birthplace":"","twitter_username":"","blog_url":"http://www.loaninterchange.com/LoanLight/","blog_feed_url":"","affiliation_name":"Loan Interchange","born_year":null,"born_month":null,"born_day":null,"tag_list":"","alias_list":null,"created_at":"Wed Jun 29 17:13:44 UTC 2011","updated_at":"Fri Jul 08 18:16:45 UTC 2011","overview":"","image":null,"degrees":[{"degree_type":"HBBA, Business/Finance","subject":"","institution":"Wilfrid Laurier University","graduated_year":1979,"graduated_month":null,"graduated_day":null},{"degree_type":"CFA, Finance","subject":"","institution":"Chartered Financial Analyst","graduated_year":1987,"graduated_month":null,"graduated_day":null}],"relationships":[{"is_past":false,"title":"President","firm":{"name":"Loan Interchange","permalink":"loan-interchange","type_of_entity":"company","image":null}},{"is_past":true,"title":"VP, Institutional Equities","firm":{"name":"Wedbush Securities","permalink":"wedbush-securities","type_of_entity":"financial_org","image":null}},{"is_past":true,"title":"Commercial Loan Origination and Note Transactions","firm":{"name":"The Helvetica Group","permalink":"the-helvetica-group","type_of_entity":"financial_org","image":null}},{"is_past":true,"title":"VP, Institutional Equities (NYC)","firm":{"name":"TD Securities Inc USA","permalink":"td-securities-inc-usa","type_of_entity":"financial_org","image":null}}],"investments":[],"milestones":[],"video_embeds":[],"external_links":[],"web_presences":[{"external_url":"http://www.linkedin.com/in/trudymsmit","title":"LinkedIn"},{"external_url":"http://www.twitter.com/LoanInterchange","title":"Twitter"}]}