{"first_name":"Umida","last_name":"Stelovska","permalink":"umida-stelovska","crunchbase_url":"http://www.crunchbase.com/person/umida-stelovska","homepage_url":null,"birthplace":null,"twitter_username":null,"blog_url":null,"blog_feed_url":null,"affiliation_name":"Unaffiliated","born_year":null,"born_month":null,"born_day":null,"tag_list":null,"alias_list":null,"created_at":"Tue Oct 18 01:36:31 UTC 2011","updated_at":"Tue Sep 04 06:42:26 UTC 2012","overview":null,"image":{"available_sizes":[[[150,150],"assets/images/resized/0020/9172/209172v2-max-150x150.jpg"],[[250,250],"assets/images/resized/0020/9172/209172v2-max-250x250.jpg"],[[450,450],"assets/images/resized/0020/9172/209172v2-max-450x450.jpg"]],"attribution":""},"degrees":[],"relationships":[{"is_past":false,"title":"Vice-President & COO","firm":{"name":"ParWinr","permalink":"parwinr","type_of_entity":"company","image":{"available_sizes":[[[150,132],"assets/images/resized/0015/8932/158932v2-max-150x150.png"],[[250,220],"assets/images/resized/0015/8932/158932v2-max-250x250.png"],[[250,220],"assets/images/resized/0015/8932/158932v2-max-450x450.png"]],"attribution":null}}}],"investments":[],"milestones":[],"video_embeds":[],"external_links":[],"web_presences":[]}