{"name":"SoftSwiss","permalink":"softswiss","crunchbase_url":"http://www.crunchbase.com/company/softswiss","homepage_url":"http://softswiss.com","blog_url":"","blog_feed_url":"","twitter_username":"softswiss","category_code":"software","number_of_employees":23,"founded_year":2007,"founded_month":6,"founded_day":5,"deadpooled_year":null,"deadpooled_month":null,"deadpooled_day":null,"deadpooled_url":null,"tag_list":"it, web-development, php-development, offshoring, nearshoring, dedicated-team, it-outsourcing, web-design, php, rubi-on-rails","alias_list":null,"email_address":"order@softswiss.com","phone_number":"+493080935730, +442081230832","description":"IT Service provider. Web development.","created_at":"Sat Jun 09 06:52:01 UTC 2012","updated_at":"Sat Jun 09 21:50:21 UTC 2012","overview":"<p>SoftSwis is an austrian IT Service company with the development center in Belarus. The SoftSwiss team consists of specialists in mathematics and information technologies who have gained significant experience in numerous projects developed for clients worldwide. Professional Web Designers, Programmers and Front-End Programmers, Project Managers ans Account managers.\nSoftSwiss provides IT services in the area of software development and offshore staffing to small and medium size businesses. Our main focus is web technologies.</p>\n\n<p>Common programming technolohies are Php, .NET, RoR, Flash. </p>","image":{"available_sizes":[[[150,35],"assets/images/resized/0019/4617/194617v2-max-150x150.png"],[[200,47],"assets/images/resized/0019/4617/194617v2-max-250x250.png"],[[200,47],"assets/images/resized/0019/4617/194617v2-max-450x450.png"]],"attribution":null},"products":[],"relationships":[{"is_past":false,"title":"CEO\\Founder`","person":{"first_name":"Ivan","last_name":"Montik","permalink":"ivan-montik","image":null}}],"competitions":[],"providerships":[],"total_money_raised":"$0","funding_rounds":[],"investments":[],"acquisition":null,"acquisitions":[],"offices":[{"description":"Austrian office","address1":"Weinbergstrasse 6","address2":"","zip_code":"7023","city":"Pöttelsdorf","state_code":null,"country_code":"AUT","latitude":null,"longitude":null}],"milestones":[],"ipo":null,"video_embeds":[],"screenshots":[{"available_sizes":[[[150,103],"assets/images/resized/0019/4616/194616v2-max-150x150.png"],[[250,173],"assets/images/resized/0019/4616/194616v2-max-250x250.png"],[[450,311],"assets/images/resized/0019/4616/194616v2-max-450x450.png"]],"attribution":null}],"external_links":[]}