{"name":"TopTechPhoto","permalink":"toptechphoto","crunchbase_url":"http://www.crunchbase.com/company/toptechphoto","homepage_url":"http://toptechphoto.com","blog_url":"","blog_feed_url":"","twitter_username":"toptechphoto","category_code":"software","number_of_employees":10,"founded_year":2009,"founded_month":11,"founded_day":null,"deadpooled_year":null,"deadpooled_month":null,"deadpooled_day":null,"deadpooled_url":null,"tag_list":"photography, technology, software, hardware, electronics, plugins","alias_list":null,"email_address":"john@toptechphoto.com","phone_number":"","description":"Tech solutions for photographers","created_at":"Thu Nov 24 10:48:52 UTC 2011","updated_at":"Sun Nov 27 16:35:48 UTC 2011","overview":"<p>TopTechPhoto is a startup company. The company produces software and hardware that helps photographers in their projects.</p>","image":{"available_sizes":[[[150,150],"assets/images/resized/0016/3882/163882v2-max-150x150.png"],[[200,200],"assets/images/resized/0016/3882/163882v2-max-250x250.png"],[[200,200],"assets/images/resized/0016/3882/163882v2-max-450x450.png"]],"attribution":null},"products":[],"relationships":[],"competitions":[],"providerships":[],"total_money_raised":"$0","funding_rounds":[],"investments":[],"acquisition":null,"acquisitions":[],"offices":[],"milestones":[],"ipo":null,"video_embeds":[],"screenshots":[],"external_links":[]}